bnrxrate/__init__.py
bnrxrate/exceptions.py
bnrxrate/holidays.py
bnrxrate/main.py
tests/__init__.py
bnrxrate-0.1.1.dist-info/LICENSE
bnrxrate-0.1.1.dist-info/METADATA
bnrxrate-0.1.1.dist-info/WHEEL
bnrxrate-0.1.1.dist-info/top_level.txt
bnrxrate-0.1.1.dist-info/RECORD
