Metadata-Version: 2.1
Name: bnrxrate
Version: 0.1.1
Summary: A Python library for fetching and processing XML data from BNR (National Bank of Romania) website
Author-email: Marian Bureata <code@bureata.com>
License: MIT License
Project-URL: homepage, https://github.com/bureata/bnrxrate
Project-URL: repository, https://github.com/bureata/bnrxrate
Project-URL: documentation, https://github.com/bureata/bnrxrate#readme
Keywords: bnr,exchange rates,XML,python,bank
Classifier: Programming Language :: Python :: 3
Classifier: License :: OSI Approved :: MIT License
Classifier: Operating System :: OS Independent
Requires-Python: >=3
License-File: LICENSE
Requires-Dist: pytz
